PandasGuanfangJiaocheng10FenzhongGaodingPandasPandasMijiXuexiPandas/README.md
PandasGuanfangJiaocheng10FenzhongGaodingPandasPandasMijiXuexiPandas/__init__.py
PandasGuanfangJiaocheng10FenzhongGaodingPandasPandasMijiXuexiPandas/__main__.py
PandasGuanfangJiaocheng10FenzhongGaodingPandasPandasMijiXuexiPandas/file.epub
PandasGuanfangJiaocheng10FenzhongGaodingPandasPandasMijiXuexiPandas/index.html
PandasGuanfangJiaocheng10FenzhongGaodingPandasPandasMijiXuexiPandas/css/__init__.py
PandasGuanfangJiaocheng10FenzhongGaodingPandasPandasMijiXuexiPandas/css/annotations.css
PandasGuanfangJiaocheng10FenzhongGaodingPandasPandasMijiXuexiPandas/css/main.css
PandasGuanfangJiaocheng10FenzhongGaodingPandasPandasMijiXuexiPandas/css/normalize.css
PandasGuanfangJiaocheng10FenzhongGaodingPandasPandasMijiXuexiPandas/css/popup.css
PandasGuanfangJiaocheng10FenzhongGaodingPandasPandasMijiXuexiPandas/font/__init__.py
PandasGuanfangJiaocheng10FenzhongGaodingPandasPandasMijiXuexiPandas/font/fontello.eot
PandasGuanfangJiaocheng10FenzhongGaodingPandasPandasMijiXuexiPandas/font/fontello.svg
PandasGuanfangJiaocheng10FenzhongGaodingPandasPandasMijiXuexiPandas/font/fontello.ttf
PandasGuanfangJiaocheng10FenzhongGaodingPandasPandasMijiXuexiPandas/font/fontello.woff
PandasGuanfangJiaocheng10FenzhongGaodingPandasPandasMijiXuexiPandas/img/__init__.py
PandasGuanfangJiaocheng10FenzhongGaodingPandasPandasMijiXuexiPandas/img/annotator-glyph-sprite.png
PandasGuanfangJiaocheng10FenzhongGaodingPandasPandasMijiXuexiPandas/img/annotator-icon-sprite.png
PandasGuanfangJiaocheng10FenzhongGaodingPandasPandasMijiXuexiPandas/img/apple-touch-icon.png
PandasGuanfangJiaocheng10FenzhongGaodingPandasPandasMijiXuexiPandas/img/cancelfullscreen.png
PandasGuanfangJiaocheng10FenzhongGaodingPandasPandasMijiXuexiPandas/img/close.png
PandasGuanfangJiaocheng10FenzhongGaodingPandasPandasMijiXuexiPandas/img/fullscreen.png
PandasGuanfangJiaocheng10FenzhongGaodingPandasPandasMijiXuexiPandas/img/loader.gif
pandas_guanfang_jiaocheng_10_fenzhong_gaoding_pandas_pandas_miji_xuexi_pandas-2024.3.2.0.dist-info/METADATA
pandas_guanfang_jiaocheng_10_fenzhong_gaoding_pandas_pandas_miji_xuexi_pandas-2024.3.2.0.dist-info/WHEEL
pandas_guanfang_jiaocheng_10_fenzhong_gaoding_pandas_pandas_miji_xuexi_pandas-2024.3.2.0.dist-info/entry_points.txt
pandas_guanfang_jiaocheng_10_fenzhong_gaoding_pandas_pandas_miji_xuexi_pandas-2024.3.2.0.dist-info/top_level.txt
pandas_guanfang_jiaocheng_10_fenzhong_gaoding_pandas_pandas_miji_xuexi_pandas-2024.3.2.0.dist-info/RECORD
