Metadata-Version: 2.1
Name: pandas-guanfang-jiaocheng-10-fenzhong-gaoding-pandas-pandas-miji-xuexi-pandas
Version: 2024.3.2.0
Summary: Pandas 官方教程（10 分钟搞定 Pandas、Pandas 秘籍、学习 Pandas）
Home-page: https://github.com/apachecn/pandas-guanfang-jiaocheng-10-fenzhong-gaoding-pandas-pandas-miji-xuexi-pandas
Author: ApacheCN
Author-email: apachecn@163.com
License: UNKNOWN
Platform: UNKNOWN
Classifier: Development Status :: 4 - Beta
Classifier: Environment :: Console
Classifier: Intended Audience :: Developers
Classifier: Intended Audience :: End Users/Desktop
Classifier: License :: Other/Proprietary License
Classifier: Natural Language :: Chinese (Simplified)
Classifier: Natural Language :: English
Classifier: Operating System :: OS Independent
Classifier: Programming Language :: Python :: 3
Classifier: Programming Language :: Python :: 3 :: Only
Classifier: Programming Language :: Python :: 3.6
Classifier: Programming Language :: Python :: 3.7
Classifier: Topic :: Text Processing :: Markup :: Markdown
Classifier: Topic :: Text Processing :: Markup :: HTML
Classifier: Topic :: Internet :: WWW/HTTP
Classifier: Topic :: Software Development :: Documentation
Classifier: Topic :: Documentation
Requires-Python: >=3.6
